LbNightlyTools/ArtifactsServer.py
LbNightlyTools/BuildLogScanner.py
LbNightlyTools/BuildMethods.py
LbNightlyTools/CheckSlotPreconditions.py
LbNightlyTools/CheckoutMethods.py
LbNightlyTools/Configuration.py
LbNightlyTools/GetNightlyRefs.py
LbNightlyTools/GitlabUtils.py
LbNightlyTools/HTMLUtils.py
LbNightlyTools/LbScriptsUtils.py
LbNightlyTools/MergeRequestBuilds.py
LbNightlyTools/ProcUtils.py
LbNightlyTools/Repository.py
LbNightlyTools/Utils.py
LbNightlyTools/__init__.py
LbNightlyTools/Scripts/Build.py
LbNightlyTools/Scripts/Checkout.py
LbNightlyTools/Scripts/CollectBuildLogs.py
LbNightlyTools/Scripts/Common.py
LbNightlyTools/Scripts/EnabledSlots.py
LbNightlyTools/Scripts/GitlabMR.py
LbNightlyTools/Scripts/Index.py
LbNightlyTools/Scripts/Install.py
LbNightlyTools/Scripts/Preconditions.py
LbNightlyTools/Scripts/Release.py
LbNightlyTools/Scripts/Test.py
LbNightlyTools/Scripts/__init__.py
LbNightlyTools/Scripts/_entry_points.py
LbNightlyTools/Scripts/extract.php
LbNightlyTools/Scripts/listzip.php
LbNightlyTools/Scripts/wrapcmd.py
LbNightlyTools/tests/__init__.py
LbNightlyTools/tests/ci-test-hook-content.json
LbNightlyTools/tests/test_apptainer.py
LbNightlyTools/tests/test_build.py
LbNightlyTools/tests/test_build_script.py
LbNightlyTools/tests/test_checkout.py
LbNightlyTools/tests/test_checkout_script.py
LbNightlyTools/tests/test_config_load.py
LbNightlyTools/tests/test_config_pickle.py
LbNightlyTools/tests/test_configuration.py
LbNightlyTools/tests/test_configuration_check.py
LbNightlyTools/tests/test_copytree.py
LbNightlyTools/tests/test_coverity_support.py
LbNightlyTools/tests/test_enabled_slots_script.py
LbNightlyTools/tests/test_gitlab_mr_script.py
LbNightlyTools/tests/test_indexer.py
LbNightlyTools/tests/test_install.py
LbNightlyTools/tests/test_jobconfig.py
LbNightlyTools/tests/test_merge_request_builds.py
LbNightlyTools/tests/test_pack.py
LbNightlyTools/tests/test_precond.py
LbNightlyTools/tests/test_rel_gen_script.py
LbNightlyTools/tests/test_release_poll.py
lbnightlytools-4.0.20.dist-info/licenses/COPYING
lbnightlytools-4.0.20.dist-info/METADATA
lbnightlytools-4.0.20.dist-info/WHEEL
lbnightlytools-4.0.20.dist-info/entry_points.txt
lbnightlytools-4.0.20.dist-info/top_level.txt
lbnightlytools-4.0.20.dist-info/RECORD
