Metadata-Version: 2.4
Name: LbNightlyTools
Version: 4.0.20
Summary: LHCb Nightly tools
Author-email: CERN - LHCb Core Software <lhcb-core-soft@cern.ch>
License-Expression: GPL-3.0-or-later
Project-URL: Homepage, https://gitlab.cern.ch/lhcb-core/LbNightlyTools
Classifier: Development Status :: 4 - Beta
Classifier: Intended Audience :: Developers
Classifier: Topic :: Software Development :: Build Tools
Requires-Python: >=3.9
License-File: COPYING
Requires-Dist: LbEnv
Requires-Dist: LbCommon>=0.0.7
Requires-Dist: LbDevTools
Requires-Dist: lbinstall
Requires-Dist: python-gitlab
Requires-Dist: CouchDB
Requires-Dist: tabulate
Requires-Dist: joblib
Requires-Dist: GitPython
Requires-Dist: networkx
Requires-Dist: pyyaml
Requires-Dist: decorator
Provides-Extra: dev
Requires-Dist: build; extra == "dev"
Requires-Dist: pytest; extra == "dev"
Requires-Dist: pytest-cov; extra == "dev"
Dynamic: license-file
